discord_embed_extensions/__init__.py
discord_embed_extensions/__main__.py
discord_embed_extensions-1.0.13.dist-info/METADATA
discord_embed_extensions-1.0.13.dist-info/WHEEL
discord_embed_extensions-1.0.13.dist-info/top_level.txt
discord_embed_extensions-1.0.13.dist-info/RECORD
