Metadata-Version: 2.1
Name: discord-embed-extensions
Version: 1.0.13
Summary: discord.Embed's extensions 
Home-page: https://github.com/Req-kun/discord_embed_extensions
Author: Req
License: MIT
Keywords: discord_embed_extensions discord_extension discord embed discord_embed
Platform: UNKNOWN
Classifier: License :: OSI Approved :: MIT License
Classifier: Programming Language :: Python :: 3.9
Requires-Dist: discord.py
